browsers/__init__.py
browsers/browsers.cpython-313-darwin.so
rsbrowsers-0.1.0a2.dist-info/METADATA
rsbrowsers-0.1.0a2.dist-info/WHEEL
rsbrowsers-0.1.0a2.dist-info/RECORD
