Metadata-Version: 2.4
Name: rsbrowsers
Version: 0.1.0a2
Classifier: Development Status :: 5 - Production/Stable
Classifier: License :: OSI Approved :: MIT License
Classifier: Topic :: Internet :: WWW/HTTP :: Browsers
Classifier: Topic :: Software Development :: Libraries :: Python Modules
Classifier: Programming Language :: Python :: 3
Classifier: Programming Language :: Python :: 3.9
Classifier: Programming Language :: Python :: 3.10
Classifier: Programming Language :: Python :: 3.11
Classifier: Programming Language :: Python :: 3.12
Classifier: Programming Language :: Python :: 3.13
Classifier: Programming Language :: Python :: Implementation :: CPython
Classifier: Programming Language :: Python :: Implementation :: PyPy
Classifier: Programming Language :: Rust
Summary: Find and launch browsers.
Home-Page: https://github.com/roniemartinez/rsbrowsers
Author: Ronie Martinez <ronmarti18@gmail.com>
Author-email: Ronie Martinez <ronmarti18@gmail.com>
License: MIT
Requires-Python: >=3.8
Project-URL: Source Code, https://github.com/roniemartinez/rsbrowsers
